pspsmgen.py
pspsmgen-0.0.2.dist-info/METADATA
pspsmgen-0.0.2.dist-info/WHEEL
pspsmgen-0.0.2.dist-info/licenses/LICENSE.txt
pspsmgen-0.0.2.dist-info/RECORD
