Metadata-Version: 2.1
Name: pspsmgen
Version: 0.0.2
Summary: Pspsmgen is a 3d pore-scale Pre-Salt model generator to simulate	petrophysical properties.
Project-URL: Homepage, https://github.com/ronaldohj/pspsmgen
Author-email: ronaldohj <ronaldohj@hotmail.com>
License-File: LICENSE.txt
Classifier: License :: OSI Approved :: MIT License
Classifier: Operating System :: OS Independent
Classifier: Programming Language :: Python :: 3
Requires-Python: >=3.7
